sammon/sammon.py
sammon_mapping-0.0.1.dist-info/METADATA
sammon_mapping-0.0.1.dist-info/WHEEL
sammon_mapping-0.0.1.dist-info/top_level.txt
sammon_mapping-0.0.1.dist-info/RECORD
