Metadata-Version: 2.1
Name: sammon-mapping
Version: 0.0.1
Author: Dilan Perera
